[
  {
    "id": "0128-央行利率",
    "date": "2026-01-28",
    "title": "央行利率決議",
    "market": "TW",
    "type": "critical",
    "trend": "neutral",
    "relatedStocks": [],
    "description": "台灣央行公布利率決議。",
    "strategy": "關注是否升息或降息，影響台幣匯率及股市。"
  },
  {
    "id": "0129-FOMC會議",
    "date": "2026-01-29",
    "title": "FOMC利率決議",
    "market": "US",
    "type": "critical",
    "trend": "neutral",
    "relatedStocks": [],
    "description": "美國聯準會（FOMC）公布利率決議。",
    "strategy": "關注是否升息或降息，影響美元匯率及美股。"
  },
  {
    "id": "0130-美國PPI",
    "date": "2026-01-30",
    "title": "美國PPI公布",
    "market": "US",
    "type": "critical",
    "trend": "neutral",
    "relatedStocks": [],
    "description": "公布美國2026年1月生產者物價指數（PPI），觀察美國通膨。",
    "strategy": "關注PPI數據，判斷聯準會升息或降息。"
  },
  {
    "id": "0131-台灣PMI",
    "date": "2026-01-31",
    "title": "台灣PMI預估",
    "market": "TW",
    "type": "critical",
    "trend": "neutral",
    "relatedStocks": [],
    "description": "預估台灣2026年1月PMI。",
    "strategy": "關注PMI是否高於50，判斷台股多空。"
  },
  {
    "id": "0131-中國PMI",
    "date": "2026-01-31",
    "title": "中國PMI公布",
    "market": "CN",
    "type": "critical",
    "trend": "neutral",
    "relatedStocks": [],
    "description": "公布中國1月官方製造業PMI。",
    "strategy": "關注PMI是否高於50，判斷中國經濟多空。"
  },
  {
    "id": "0202-AMD財報",
    "date": "2026-02-03",
    "title": "AMD公布財報",
    "market": "US",
    "type": "corporate",
    "trend": "neutral",
    "relatedStocks": [
      "AMD (AMD)"
    ],
    "description": "AMD公布2025年第四季度及全年財報。",
    "strategy": "關注營收、獲利及未來展望。"
  },
  {
    "id": "0203-美國PMI",
    "date": "2026-02-03",
    "title": "美國PMI公布",
    "market": "US",
    "type": "critical",
    "trend": "neutral",
    "relatedStocks": [],
    "description": "公布美國2026年1月PMI。",
    "strategy": "關注PMI是否高於50，判斷美股多空。"
  },
  {
    "id": "0203-台灣PMI",
    "date": "2026-02-03",
    "title": "台灣PMI公布",
    "market": "TW",
    "type": "critical",
    "trend": "neutral",
    "relatedStocks": [],
    "description": "公布台灣2026年1月PMI。",
    "strategy": "關注PMI是否高於50，判斷台股多空。"
  },
  {
    "id": "0203-聯發科法說",
    "date": "2026-02-03",
    "title": "聯發科法說會",
    "market": "TW",
    "type": "corporate",
    "trend": "neutral",
    "relatedStocks": [
      "聯發科 (2454)"
    ],
    "description": "聯發科舉行法說會，說明營運狀況。",
    "strategy": "關注手機晶片、AI晶片等業務發展。"
  },
  {
    "id": "0205-非農就業",
    "date": "2026-02-06",
    "title": "美國非農就業",
    "market": "US",
    "type": "critical",
    "trend": "neutral",
    "relatedStocks": [],
    "description": "公布美國1月非農就業數據。",
    "strategy": "關注就業數據，判斷聯準會貨幣政策。"
  },
  {
    "id": "0207-台積電ADR",
    "date": "2026-02-07",
    "title": "台積電ADR",
    "market": "US",
    "type": "hot",
    "trend": "bull",
    "relatedStocks": [
      "台積電 (2330)"
    ],
    "description": "關注台積電ADR走勢，觀察外資對台積電看法。",
    "strategy": "ADR上漲，有利台積電股價。"
  },
  {
    "id": "0210-台達電法說",
    "date": "2026-02-10",
    "title": "台達電法說會",
    "market": "TW",
    "type": "corporate",
    "trend": "neutral",
    "relatedStocks": [
      "台達電 (2308)"
    ],
    "description": "台達電舉行法說會，說明營運狀況。",
    "strategy": "關注電源供應器、電動車等業務發展。"
  },
  {
    "id": "0212-美國CPI",
    "date": "2026-02-12",
    "title": "美國CPI公布",
    "market": "US",
    "type": "critical",
    "trend": "neutral",
    "relatedStocks": [],
    "description": "公布美國1月消費者物價指數（CPI），觀察美國通膨。",
    "strategy": "關注CPI數據，判斷聯準會升息或降息。"
  },
  {
    "id": "0212-美國PPI",
    "date": "2026-02-12",
    "title": "美國PPI公布",
    "market": "US",
    "type": "critical",
    "trend": "neutral",
    "relatedStocks": [],
    "description": "公布美國2026年1月生產者物價指數（PPI），觀察美國通膨。",
    "strategy": "關注PPI數據，判斷聯準會升息或降息。"
  },
  {
    "id": "0215-台灣CPI",
    "date": "2026-02-15",
    "title": "台灣CPI公布",
    "market": "TW",
    "type": "critical",
    "trend": "neutral",
    "relatedStocks": [],
    "description": "公布台灣1月消費者物價指數（CPI），觀察台灣通膨。",
    "strategy": "關注CPI數據，判斷央行貨幣政策。"
  },
  {
    "id": "0218-聯電法說",
    "date": "2026-02-18",
    "title": "聯電法說會",
    "market": "TW",
    "type": "corporate",
    "trend": "neutral",
    "relatedStocks": [
      "聯電 (2303)"
    ],
    "description": "聯電舉行法說會，說明營運狀況。",
    "strategy": "關注成熟製程產能利用率及未來展望。"
  },
  {
    "id": "0220-日月光法說",
    "date": "2026-02-20",
    "title": "日月光法說會",
    "market": "TW",
    "type": "corporate",
    "trend": "neutral",
    "relatedStocks": [
      "日月光投控 (3711)"
    ],
    "description": "日月光投控舉行法說會，說明營運狀況。",
    "strategy": "關注封測產業景氣及先進封裝技術發展。"
  },
  {
    "id": "0225-NVIDIA財報",
    "date": "2026-02-25",
    "title": "NVIDIA公布財報",
    "market": "US",
    "type": "corporate",
    "trend": "bull",
    "relatedStocks": [
      "NVIDIA (NVDA)"
    ],
    "description": "NVIDIA公布2026財年Q4財報。",
    "strategy": "關注營收、獲利及Blackwell架構晶片銷售。"
  },
  {
    "id": "0228-台灣PMI",
    "date": "2026-02-28",
    "title": "台灣PMI預估",
    "market": "TW",
    "type": "critical",
    "trend": "neutral",
    "relatedStocks": [],
    "description": "預估台灣2026年2月PMI。",
    "strategy": "關注PMI是否高於50，判斷台股多空。"
  },
  {
    "id": "0228-外銷訂單",
    "date": "2026-02-28",
    "title": "台灣外銷訂單",
    "market": "TW",
    "type": "critical",
    "trend": "bull",
    "relatedStocks": [],
    "description": "公布台灣2026年1月外銷訂單，觀察台灣出口狀況。",
    "strategy": "關注外銷訂單金額及年增率，判斷出口趨勢。"
  }
]